MANIFEST.in
README.md
setup.py
documentation/API-Hackathon.md
documentation/Makefile
documentation/README.md
documentation/UML.md
documentation/man/termicoder-code.1
documentation/man/termicoder-config-autocomplete-install.1
documentation/man/termicoder-config-autocomplete-show.1
documentation/man/termicoder-config-autocomplete.1
documentation/man/termicoder-config.1
documentation/man/termicoder-debug.1
documentation/man/termicoder-repl.1
documentation/man/termicoder-setup.1
documentation/man/termicoder-submit.1
documentation/man/termicoder-test.1
documentation/man/termicoder-view-contest.1
documentation/man/termicoder-view-problem.1
documentation/man/termicoder-view-this.1
documentation/man/termicoder-view.1
documentation/man/termicoder.1
documentation/sphinix/Makefile
documentation/sphinix/conf.py
documentation/sphinix/index.rst
documentation/sphinix/make.bat
documentation/sphinix/termicoder.rst
documentation/sphinix/_build/doctrees/environment.pickle
documentation/sphinix/_build/doctrees/index.doctree
documentation/sphinix/_build/doctrees/termicoder.doctree
documentation/sphinix/_build/html/.buildinfo
documentation/sphinix/_build/html/genindex.html
documentation/sphinix/_build/html/index.html
documentation/sphinix/_build/html/objects.inv
documentation/sphinix/_build/html/search.html
documentation/sphinix/_build/html/searchindex.js
documentation/sphinix/_build/html/termicoder.html
documentation/sphinix/_build/html/_sources/index.rst.txt
documentation/sphinix/_build/html/_sources/termicoder.rst.txt
documentation/sphinix/_build/html/_static/ajax-loader.gif
documentation/sphinix/_build/html/_static/alabaster.css
documentation/sphinix/_build/html/_static/basic.css
documentation/sphinix/_build/html/_static/comment-bright.png
documentation/sphinix/_build/html/_static/comment-close.png
documentation/sphinix/_build/html/_static/comment.png
documentation/sphinix/_build/html/_static/custom.css
documentation/sphinix/_build/html/_static/doctools.js
termicoder.egg-info/PKG-INFO
termicoder.egg-info/SOURCES.txt
termicoder.egg-info/dependency_links.txt
termicoder.egg-info/entry_points.txt
termicoder.egg-info/requires.txt
termicoder.egg-info/top_level.txt
