Metadata-Version: 2.1
Name: termicoder
Version: 0.3.0
Summary: CLI to view, code & submit problems directly from terminal
Home-page: https://github.com/termicoder/termicoder
Author: Divesh Uttamchandani
Author-email: diveshuttamchandani@gmail.com
License: MIT
Project-URL: Say Thanks!, https://saythanks.io/to/diveshuttam
Project-URL: Source, https://github.com/termicoder/termicoder/
Project-URL: Bug Reports, https://github.com/termicoder/termicoder/issues
Keywords: competitive codechef oj
Platform: UNKNOWN
Classifier: Development Status :: 3 - Alpha
Classifier: Intended Audience :: Education
Classifier: Topic :: Education
Classifier: License :: OSI Approved :: MIT License
Classifier: Programming Language :: Python :: 3.4
Classifier: Programming Language :: Python :: 3.5
Classifier: Programming Language :: Python :: 3.6
Classifier: Programming Language :: Python :: 3.7
